<?xml version="1.0" encoding="utf-8"?>
<AccpacImpExp Action="8" ProgramName="AP2100" Type="EXPORT" Version="532" ExportDateLocale="3084"><VIEW ID="AP0020" Type="4" Action="0" AllFieldSelected="0"><TABLE>AP_Invoice_Batch_Subclass</TABLE></VIEW><VIEW ID="AP0021" Type="3" Action="0" Parent="AP0020" AllFieldSelected="1"><TABLE>Invoices</TABLE></VIEW><VIEW ID="AP0022" Type="9" Action="0" Parent="AP0021" AllFieldSelected="1"><TABLE>Invoice_Details</TABLE></VIEW><VIEW ID="AP0023" Type="9" Action="0" Parent="AP0021" AllFieldSelected="1"><TABLE>Invoice_Payment_Schedules</TABLE></VIEW><VIEW ID="AP0402" Type="8" Action="4096" Parent="AP0021" AllFieldSelected="1"><TABLE>Invoice_Optional_Fields</TABLE></VIEW><VIEW ID="AP0401" Type="8" Action="4096" Parent="AP0022" AllFieldSelected="1"><TABLE>Invoice_Detail_Optional_Fields</TABLE></VIEW><DBNAME>A:\Caresoft\13-02-2024\inv temp1.xls</DBNAME><DBTYPE>Excel 2000</DBTYPE><BatchID>24893 </BatchID></AccpacImpExp>
